<?xml version="1.0" encoding="UTF-8"?>

<calendar year="2022">

	<images>img/gifts/</images>

	<day>
		<date>24</date>
		<link>https://www.google.com/search?q=24</link>
		<bg>gift_24.jpg</bg>
	</day>
	<day>
		<date>22</date>
		<link>https://www.google.com/search?q=22</link>
		<bg>gift_22.jpg</bg>
	</day>
	<day>
		<date>27</date>
		<link>https://www.google.com/search?q=27</link>
		<bg>gift_27.jpg</bg>
	</day>
	<day>
		<date>14</date>
		<link>https://www.google.com/search?q=14</link>
		<bg>gift_14.jpg</bg>
	</day>
	<day>
		<date>31</date>
		<link>https://www.google.com/search?q=31</link>
		<bg>gift_31.jpg</bg>
	</day>
	<day>
		<date>17</date>
		<link>https://www.google.com/search?q=17</link>
		<bg>gift_17.jpg</bg>
	</day>
	<day>
		<date>25</date>
		<link>https://www.google.com/search?q=25</link>
		<bg>gift_25.jpg</bg>
	</day>
	<day>
		<date>13</date>
		<link>https://www.google.com/search?q=13</link>
		<bg>gift_13.jpg</bg>
	</day>
	<day>
		<date>18</date>
		<link>https://www.google.com/search?q=18</link>
		<bg>gift_18.jpg</bg>
	</day>
	<day>
		<date>11</date>
		<link>https://www.google.com/search?q=11</link>
		<bg>gift_11.jpg</bg>
	</day>
	<day>
		<date>21</date>
		<link>https://www.google.com/search?q=21</link>
		<bg>gift_21.jpg</bg>
	</day>
	<day>
		<date>30</date>
		<link>https://www.google.com/search?q=30</link>
		<bg>gift_30.jpg</bg>
	</day>
	<day>
		<date>9</date>
		<link>https://www.google.com/search?q=9</link>
		<bg>gift_9.jpg</bg>
	</day>
	<day>
		<date>26</date>
		<link>https://www.google.com/search?q=26</link>
		<bg>gift_26.jpg</bg>
	</day>
	<day>
		<date>20</date>
		<link>https://www.google.com/search?q=20</link>
		<bg>gift_20.jpg</bg>
	</day>
	<day>
		<date>8</date>
		<link>https://www.google.com/search?q=8</link>
		<bg>gift_8.jpg</bg>
	</day>
	<day>
		<date>29</date>
		<link>https://www.google.com/search?q=29</link>
		<bg>gift_29.jpg</bg>
	</day>
	<day>
		<date>16</date>
		<link>https://www.google.com/search?q=16</link>
		<bg>gift_16.jpg</bg>
	</day>
	<day>
		<date>28</date>
		<link>https://www.google.com/search?q=28</link>
		<bg>gift_28.jpg</bg>
	</day>
	<day>
		<date>12</date>
		<link>https://www.google.com/search?q=12</link>
		<bg>gift_12.jpg</bg>
	</day>
	<day>
		<date>23</date>
		<link>https://www.google.com/search?q=23</link>
		<bg>gift_23.jpg</bg>
	</day>
	<day>
		<date>15</date>
		<link>https://www.google.com/search?q=15</link>
		<bg>gift_15.jpg</bg>
	</day>
	<day>
		<date>10</date>
		<link>https://www.google.com/search?q=10</link>
		<bg>gift_10.jpg</bg>
	</day>
	<day>
		<date>19</date>
		<link>https://www.google.com/search?q=19</link>
		<bg>gift_19.jpg</bg>
	</day>
</calendar>